tvrenamer/__init__.py
tvrenamer/cli.py
tvrenamer/constants.py
tvrenamer/exceptions.py
tvrenamer/manager.py
tvrenamer/options.py
tvrenamer/service.py
tvrenamer/cache/__init__.py
tvrenamer/cache/api.py
tvrenamer/common/__init__.py
tvrenamer/common/encodeutils.py
tvrenamer/common/table.py
tvrenamer/common/tools.py
tvrenamer/core/__init__.py
tvrenamer/core/episode.py
tvrenamer/core/formatter.py
tvrenamer/core/parser.py
tvrenamer/core/patterns.py
tvrenamer/core/renamer.py
tvrenamer/core/watcher.py
tvrenamer/processors/__init__.py
tvrenamer/processors/base.py
tvrenamer/processors/cache.py
tvrenamer/processors/noop.py
tvrenamer/processors/printer.py
tvrenamer/services/__init__.py
tvrenamer/services/base.py
tvrenamer/services/trakt_service.py
tvrenamer/services/tvdb.py
tvrenamer/tests/__init__.py
tvrenamer/tests/base.py
tvrenamer/tests/test_cli.py
tvrenamer/tests/test_manager.py
tvrenamer/tests/test_options.py
tvrenamer/tests/test_service.py
tvrenamer/tests/cache/__init__.py
tvrenamer/tests/cache/test_api.py
tvrenamer/tests/common/__init__.py
tvrenamer/tests/common/test_titlecase.py
tvrenamer/tests/common/test_tools.py
tvrenamer/tests/core/__init__.py
tvrenamer/tests/core/test_episode.py
tvrenamer/tests/core/test_formatter.py
tvrenamer/tests/core/test_parser.py
tvrenamer/tests/core/test_patterns.py
tvrenamer/tests/core/test_renamer.py
tvrenamer/tests/core/test_watcher.py
tvrenamer/tests/processors/__init__.py
tvrenamer/tests/processors/test_base.py
tvrenamer/tests/processors/test_cache.py
tvrenamer/tests/processors/test_print.py
tvrenamer/tests/services/__init__.py
tvrenamer/tests/services/test_trakt.py
tvrenamer/tests/services/test_tvdb.py
tvrenamer-0.3.0.data/data/etc/tvrenamer/gen.conf
tvrenamer-0.3.0.data/data/etc/tvrenamer/tvrenamer.conf.sample
tvrenamer-0.3.0.dist-info/DESCRIPTION.rst
tvrenamer-0.3.0.dist-info/METADATA
tvrenamer-0.3.0.dist-info/RECORD
tvrenamer-0.3.0.dist-info/WHEEL
tvrenamer-0.3.0.dist-info/entry_points.txt
tvrenamer-0.3.0.dist-info/metadata.json
tvrenamer-0.3.0.dist-info/pbr.json
tvrenamer-0.3.0.dist-info/top_level.txt
