Metadata-Version: 2.0
Name: tvrenamer
Version: 0.3.0
Summary: TV Episode Renamer
Home-page: https://github.com/shad7/tvrenamer
Author: shad7
Author-email: kenny.shad7@gmail.com
License: MIT
Keywords: tv,espisode
Platform: UNKNOWN
Classifier: Development Status :: 4 - Beta
Classifier: Environment :: Console
Classifier: Environment :: Other Environment
Classifier: License :: OSI Approved :: MIT License
Classifier: Operating System :: OS Independent
Classifier: Programming Language :: Python
Classifier: Programming Language :: Python :: 2
Classifier: Programming Language :: Python :: 2.7
Classifier: Programming Language :: Python :: 3
Classifier: Programming Language :: Python :: 3.4
Classifier: Programming Language :: Python :: Implementation :: PyPy
Classifier: Topic :: Internet
Classifier: Topic :: Multimedia
Classifier: Topic :: Software Development :: Libraries :: Python Modules
Classifier: Topic :: Utilities
Requires-Dist: PrettyTable (<0.8,>=0.7)
Requires-Dist: lockfile
Requires-Dist: oslo.config (>=1.9.0)
Requires-Dist: pbr (>=1.6.0)
Requires-Dist: six (>=1.9.0)
Requires-Dist: stevedore (>=1.5.0)
Requires-Dist: tinydb (<3.0,>=2.4)
Requires-Dist: titlecase (>=0.7.2)
Requires-Dist: trakt.py (>=2.5.1)
Requires-Dist: tvdbapi-client (>=0.1.4)
Requires-Dist: twine
